README.md
setup.py
licensetree/__init__.py
licensetree.egg-info/PKG-INFO
licensetree.egg-info/SOURCES.txt
licensetree.egg-info/dependency_links.txt
licensetree.egg-info/entry_points.txt
licensetree.egg-info/not-zip-safe
licensetree.egg-info/top_level.txt