Metadata-Version: 1.0
Name: licensetree
Version: 0.0.1
Summary: License Tree Generator for Python Projects
Home-page: http://github.com/theSage21/licensetree
Author: Arjoonn Sharma
Author-email: arjoonn.94@gmail.com
License: UNKNOWN
Keywords: licensetree,license,mapping,dependeicies
Platform: UNKNOWN
